Metadata-Version: 2.4
Name: docext
Version: 0.1.14
Summary: Onprem information extraction from documents
Home-page: https://github.com/nanonets/docext
Author: Souvik Mandal
Author-email: souvik@nanonets.com
Classifier: Programming Language :: Python :: 3.11
Classifier: License :: OSI Approved :: MIT License
Classifier: Operating System :: OS Independent
Requires-Python: >=3.11
License-File: LICENSE
Requires-Dist: accelerate
Requires-Dist: gradio==5.23.2
Requires-Dist: json-repair
Requires-Dist: litellm
Requires-Dist: loguru
Requires-Dist: mdpd
Requires-Dist: numpy
Requires-Dist: pandas
Requires-Dist: pdf2image
Requires-Dist: PyMuPDF
Requires-Dist: python-dotenv
Requires-Dist: python-levenshtein==0.27.1
Requires-Dist: requests
Requires-Dist: setuptools
Requires-Dist: tabulate
Requires-Dist: tenacity
Requires-Dist: transformers<4.53.0,>=4.51.1
Requires-Dist: types-requests
Requires-Dist: vllm==0.8.3
Requires-Dist: xgrammar==0.1.17
Provides-Extra: dev
Requires-Dist: pre-commit; extra == "dev"
Dynamic: author
Dynamic: author-email
Dynamic: classifier
Dynamic: description
Dynamic: description-content-type
Dynamic: home-page
Dynamic: license-file
Dynamic: provides-extra
Dynamic: requires-dist
Dynamic: requires-python
Dynamic: summary
